ipython_odoo/__init__.py
ipython_odoo/access.py
ipython_odoo/connect.py
ipython_odoo/hierarchy.py
ipython_odoo/magic.py
ipython_odoo/main.py
ipython_odoo/model_names.py
ipython_odoo/procurement_rules.py
ipython_odoo/property_values.py
ipython_odoo/recordset_formatting.py
ipython_odoo/ref.py
ipython_odoo/related_fields.py
ipython_odoo/table.py
ipython_odoo/tables.py
ipython_odoo/tracer.py
ipython_odoo-0.5.2.dist-info/LICENSE
ipython_odoo-0.5.2.dist-info/METADATA
ipython_odoo-0.5.2.dist-info/WHEEL
ipython_odoo-0.5.2.dist-info/RECORD
