Metadata-Version: 2.1
Name: ipython-odoo
Version: 0.5.2
Summary: 
Author: Dmitry Voronin
Author-email: dimka665@gmail.com
Requires-Python: >=3.10,<4.0
Classifier: Programming Language :: Python :: 3
Classifier: Programming Language :: Python :: 3.10
Classifier: Programming Language :: Python :: 3.11
Requires-Dist: texttable (>=1.7.0,<2.0.0)
